virtualpreference/storage/__init__.py
virtualpreference/storage/core.py
virtualpreference/storage/django.py
virtualpreference-1.0.0.dist-info/METADATA
virtualpreference-1.0.0.dist-info/WHEEL
virtualpreference-1.0.0.dist-info/top_level.txt
virtualpreference-1.0.0.dist-info/RECORD
