Metadata-Version: 2.1
Name: virtualpreference
Version: 1.0.0
Summary: Virtual Preference APIs Connector
Author: Virtual Preference Team
Author-email: team@virtualpreference.com
Requires-Dist: django
Requires-Dist: requests
Requires-Dist: wheel
Requires-Dist: termcolor
